student_helper/__init__.py
student_helper/error.py
student_helper/files.py
student_helper/organization.py
student_helper/biblio/__init__.py
student_helper/biblio/integrali.py
student_helper/biblio/matplotlib.py
student_helper/biblio/numpy.py
student_helper/ojectspython/__init__.py
student_helper/ojectspython/massivinfo.py
student_helper/ojectspython/operators.py
student_helper/ojectspython/str_and_number.py
student_helper/practic/__init__.py
student_helper/practic/azbuka.py
student_helper/practic/integrali.py
student_helper/practic/mpl_practic_2.py
student_helper/practic/pandas+excel.py
student_helper/practic/work_file.py
student_helper/practic/work_pandas.py
student_helper/worck_class/__init__.py
student_helper/worck_class/create_class.py
student_helper/worck_class/incapsulClass.py
student_helper/worck_class/nasledClass.py
student_helper/worck_class/specMetClass.py
student_helper-1.0.1.dist-info/METADATA
student_helper-1.0.1.dist-info/WHEEL
student_helper-1.0.1.dist-info/top_level.txt
student_helper-1.0.1.dist-info/RECORD
